sample_project/__init__.py
sample_project/__version__.py
sample_project/sample_project.py
second_pkg_joeyding-0.0.7.dist-info/LICENSE
second_pkg_joeyding-0.0.7.dist-info/METADATA
second_pkg_joeyding-0.0.7.dist-info/WHEEL
second_pkg_joeyding-0.0.7.dist-info/top_level.txt
second_pkg_joeyding-0.0.7.dist-info/RECORD
